aio_watts_vision/__init__.py
aio_watts_vision/__main__.py
aio_watts_vision/abstract_auth.py
aio_watts_vision/auth.py
aio_watts_vision/token_manager.py
aio_watts_vision/watts_vision_api.py
aio_watts_vision/models/__init__.py
aio_watts_vision/models/base.py
aio_watts_vision/models/enums.py
aio_watts_vision/models/smarthome.py
aio_watts_vision/models/user.py
aio_watts_vision/models/util.py
aio_watts_vision-0.1.0.dist-info/LICENSE.MD
aio_watts_vision-0.1.0.dist-info/METADATA
aio_watts_vision-0.1.0.dist-info/WHEEL
aio_watts_vision-0.1.0.dist-info/top_level.txt
aio_watts_vision-0.1.0.dist-info/RECORD
