Metadata-Version: 2.1
Name: aio-watts-vision
Version: 0.1.0
Summary: ##### ToDo: Rewrite me #####
Home-page: https://github.com/mjkl-gh/aio-watts-vision
Author: mjkl-gh
Author-email: 9350991+mjkl-gh@users.noreply.github.com
Project-URL: Bug Tracker, https://github.com/mjkl-gh/aio-watts-vision/-/issues
Project-URL: repository, https://github.com/mjkl-gh/aio-watts-vision
Classifier: Development Status :: 3 - Alpha
Classifier: Intended Audience :: Developers
Classifier: License :: OSI Approved :: Apache Software License
Classifier: Programming Language :: Python
Classifier: Programming Language :: Python :: 3
Classifier: Programming Language :: Python :: 3.7
Classifier: Programming Language :: Python :: 3.8
Classifier: Programming Language :: Python :: Implementation :: CPython
Classifier: Programming Language :: Python :: Implementation :: PyPy
Requires-Python: >=3.9
License-File: LICENSE.MD
Requires-Dist: setuptools
Provides-Extra: rest
Requires-Dist: Sphinx ; extra == 'rest'
